hook/__init__.py
hook/cmd.py
sceptre_cmd_hook-1.0.0.dist-info/METADATA
sceptre_cmd_hook-1.0.0.dist-info/WHEEL
sceptre_cmd_hook-1.0.0.dist-info/entry_points.txt
sceptre_cmd_hook-1.0.0.dist-info/top_level.txt
sceptre_cmd_hook-1.0.0.dist-info/RECORD
